symcollab/moe/__init__.py
symcollab/moe/callable_registry.py
symcollab/moe/check.py
symcollab/moe/collisions.py
symcollab/moe/custom.py
symcollab/moe/filtered_generator.py
symcollab/moe/generator.py
symcollab/moe/invertibility.py
symcollab/moe/moo.py
symcollab/moe/program.py
symcollab/moe/schedule.py
symcollab/moe/syntactic_check.py
symcollab/moe/gui/moo_client.py
symcollab/moe/website/__init__.py
symcollab/moe/website/run.py
symcollab/moe/website/routes/__init__.py
symcollab/moe/website/routes/checker.py
symcollab/moe/website/routes/custom.py
symcollab/moe/website/routes/program.py
symcollab/moe/website/routes/random.py
symcollab/moe/website/routes/utils.py
symcollab/moe/website/static/unifchaincheck.js
symcollab/moe/website/static/css/style.css
symcollab/moe/website/templates/base.html
symcollab/moe/website/templates/checker.html
symcollab/moe/website/templates/custom.html
symcollab/moe/website/templates/program.html
symcollab/moe/website/templates/program_create.html
symcollab/moe/website/templates/random.html
symcollab_moe-0.1.3.data/data/symcollab/moe/website/static/unifchaincheck.js
symcollab_moe-0.1.3.data/data/symcollab/moe/website/static/css/style.css
symcollab_moe-0.1.3.data/data/symcollab/moe/website/templates/base.html
symcollab_moe-0.1.3.data/data/symcollab/moe/website/templates/checker.html
symcollab_moe-0.1.3.data/data/symcollab/moe/website/templates/custom.html
symcollab_moe-0.1.3.data/data/symcollab/moe/website/templates/program.html
symcollab_moe-0.1.3.data/data/symcollab/moe/website/templates/program_create.html
symcollab_moe-0.1.3.data/data/symcollab/moe/website/templates/random.html
symcollab_moe-0.1.3.data/scripts/moe_tool
symcollab_moe-0.1.3.data/scripts/moe_website
symcollab_moe-0.1.3.dist-info/METADATA
symcollab_moe-0.1.3.dist-info/WHEEL
symcollab_moe-0.1.3.dist-info/top_level.txt
symcollab_moe-0.1.3.dist-info/RECORD
